onomatool/__init__.py
onomatool/cli.py
onomatool/config.py
onomatool/conflict_resolver.py
onomatool/file_collector.py
onomatool/file_dispatcher.py
onomatool/llm_integration.py
onomatool/models.py
onomatool/prompts.py
onomatool/renamer.py
onomatool/processors/markitdown_processor.py
onomatool/processors/text_processor.py
onomatool/utils/image_utils.py
onomatool-0.1.2.dist-info/licenses/LICENSE
onomatool-0.1.2.dist-info/METADATA
onomatool-0.1.2.dist-info/WHEEL
onomatool-0.1.2.dist-info/entry_points.txt
onomatool-0.1.2.dist-info/top_level.txt
onomatool-0.1.2.dist-info/RECORD
