Metadata-Version: 2.4
Name: onomatool
Version: 0.1.2
Summary: AI-powered file renaming tool with LLM integration
Author-email: Robin Collins <Robin.F.Collins@outlook.com>
Maintainer-email: Robin Collins <Robin.F.Collins@outlook.com>
License-Expression: MIT AND (Apache-2.0 OR BSD-2-Clause)
Project-URL: Homepage, https://github.com/robin-collins/Onoma
Project-URL: Repository, https://github.com/robin-collins/Onoma
Project-URL: Documentation, https://github.com/robin-collins/Onoma#readme
Project-URL: Bug Tracker, https://github.com/robin-collins/Onoma/issues
Project-URL: Changelog, https://github.com/robin-collins/Onoma/blob/main/CHANGELOG.md
Keywords: ai,llm,file-rename,automation,cli
Classifier: Development Status :: 4 - Beta
Classifier: Environment :: Console
Classifier: Intended Audience :: Developers
Classifier: Intended Audience :: End Users/Desktop
Classifier: Operating System :: OS Independent
Classifier: Programming Language :: Python :: 3
Classifier: Programming Language :: Python :: 3.10
Classifier: Programming Language :: Python :: 3.11
Classifier: Programming Language :: Python :: 3.12
Classifier: Programming Language :: Python :: 3.13
Classifier: Topic :: Software Development :: Libraries :: Python Modules
Classifier: Topic :: System :: Filesystems
Classifier: Topic :: Utilities
Requires-Python: >=3.10
License-File: LICENSE
Requires-Dist: markitdown>=0.1.2
Requires-Dist: openai>=1.86.0
Requires-Dist: google-genai>=1.20.0
Requires-Dist: tomli>=2.2.1
Requires-Dist: tiktoken>=0.9.0
Requires-Dist: pydantic>=2.11.7
Requires-Dist: httpx>=0.28.1
Requires-Dist: chardet>=5.2.0
Requires-Dist: cairosvg>=2.8.2
Requires-Dist: pillow>=11.2.1
Requires-Dist: PyMuPDF>=1.26.1
Requires-Dist: ruff>=0.12.0
Requires-Dist: toml>=0.10.2
Provides-Extra: dev
Requires-Dist: pytest>=8.4.0; extra == "dev"
Requires-Dist: pytest-cov>=4.0.0; extra == "dev"
Requires-Dist: ruff>=0.11.13; extra == "dev"
Dynamic: license-file
